[{"alignedWord": "drag", "case": "success", "end": 0.34, "endOffset": 4, "phones": [{"duration": 0.05, "phone": "d_B"}, {"duration": 0.09, "phone": "r_I"}, {"duration": 0.11, "phone": "ae_I"}, {"duration": 0.08, "phone": "g_E"}], "start": 0.01, "startOffset": 0, "word": "drag"}, {"alignedWord": "men", "case": "success", "end": 0.6100000000000001, "endOffset": 8, "phones": [{"duration": 0.06, "phone": "m_B"}, {"duration": 0.11, "phone": "eh_I"}, {"duration": 0.1, "phone": "n_E"}], "start": 0.34, "startOffset": 5, "word": "men"}, {"alignedWord": "cows", "case": "success", "end": 0.95, "endOffset": 13, "phones": [{"duration": 0.07, "phone": "k_B"}, {"duration": 0.15, "phone": "aw_I"}, {"duration": 0.09, "phone": "z_E"}], "start": 0.64, "startOffset": 9, "word": "cows"}, {"alignedWord": "slow", "case": "success", "end": 1.28, "endOffset": 18, "phones": [{"duration": 0.1, "phone": "s_B"}, {"duration": 0.1, "phone": "l_I"}, {"duration": 0.12, "phone": "ow_E"}], "start": 0.96, "startOffset": 14, "word": "slow"}, {"alignedWord": "hold", "case": "success", "end": 1.58, "endOffset": 23, "phones": [{"duration": 0.07, "phone": "hh_B"}, {"duration": 0.06, "phone": "ow_I"}, {"duration": 0.11, "phone": "l_I"}, {"duration": 0.06, "phone": "d_E"}], "start": 1.28, "startOffset": 19, "word": "hold"}, {"alignedWord": "hands", "case": "success", "end": 1.9100000000000001, "endOffset": 29, "phones": [{"duration": 0.07, "phone": "hh_B"}, {"duration": 0.09, "phone": "ae_I"}, {"duration": 0.09, "phone": "n_I"}, {"duration": 0.07, "phone": "z_E"}], "start": 1.59, "startOffset": 24, "word": "hands"}, {"alignedWord": "books", "case": "success", "end": 2.25, "endOffset": 35, "phones": [{"duration": 0.08, "phone": "b_B"}, {"duration": 0.11, "phone": "uh_I"}, {"duration": 0.08, "phone": "k_I"}, {"duration": 0.07, "phone": "s_E"}], "start": 1.91, "startOffset": 30, "word": "books"}, {"alignedWord": "old", "case": "success", "end": 2.58, "endOffset": 39, "phones": [{"duration": 0.12, "phone": "ow_B"}, {"duration": 0.14, "phone": "l_I"}, {"duration": 0.07, "phone": "d_E"}], "start": 2.25, "startOffset": 36, "word": "old"}, {"alignedWord": "read", "case": "success", "end": 2.84, "endOffset": 44, "phones": [{"duration": 0.08, "phone": "r_B"}, {"duration": 0.11, "phone": "eh_I"}, {"duration": 0.07, "phone": "d_E"}], "start": 2.58, "startOffset": 40, "word": "read"}, {"alignedWord": "men", "case": "success", "end": 3.17, "endOffset": 48, "phones": [{"duration": 0.08, "phone": "m_B"}, {"duration": 0.12, "phone": "eh_I"}, {"duration": 0.1, "phone": "n_E"}], "start": 2.87, "startOffset": 45, "word": "men"}, {"alignedWord": "books", "case": "success", "end": 3.5, "endOffset": 54, "phones": [{"duration": 0.09, "phone": "b_B"}, {"duration": 0.11, "phone": "uh_I"}, {"duration": 0.07, "phone": "k_I"}, {"duration": 0.05, "phone": "s_E"}], "start": 3.18, "startOffset": 49, "word": "books"}, {"alignedWord": "kind", "case": "success", "end": 3.8699999999999997, "endOffset": 59, "phones": [{"duration": 0.06, "phone": "k_B"}, {"duration": 0.15, "phone": "ay_I"}, {"duration": 0.07, "phone": "n_I"}, {"duration": 0.06, "phone": "d_E"}], "start": 3.53, "startOffset": 55, "word": "kind"}, {"alignedWord": "hunt", "case": "success", "end": 4.140000000000001, "endOffset": 64, "phones": [{"duration": 0.05, "phone": "hh_B"}, {"duration": 0.12, "phone": "ah_I"}, {"duration": 0.02, "phone": "n_I"}, {"duration": 0.08, "phone": "t_E"}], "start": 3.87, "startOffset": 60, "word": "hunt"}, {"alignedWord": "dogs", "case": "success", "end": 4.49, "endOffset": 69, "phones": [{"duration": 0.07, "phone": "d_B"}, {"duration": 0.14, "phone": "ao_I"}, {"duration": 0.07, "phone": "g_I"}, {"duration": 0.04, "phone": "z_E"}], "start": 4.17, "startOffset": 65, "word": "dogs"}, {"alignedWord": "cats", "case": "success", "end": 4.7700000000000005, "endOffset": 74, "phones": [{"duration": 0.06, "phone": "k_B"}, {"duration": 0.09, "phone": "ae_I"}, {"duration": 0.06, "phone": "t_I"}, {"duration": 0.07, "phone": "s_E"}], "start": 4.49, "startOffset": 70, "word": "cats"}, {"alignedWord": "loud", "case": "success", "end": 5.08, "endOffset": 79, "phones": [{"duration": 0.08, "phone": "l_B"}, {"duration": 0.13, "phone": "aw_I"}, {"duration": 0.07, "phone": "d_E"}], "start": 4.8, "startOffset": 75, "word": "loud"}, {"alignedWord": "like", "case": "success", "end": 5.390000000000001, "endOffset": 84, "phones": [{"duration": 0.1, "phone": "l_B"}, {"duration": 0.09, "phone": "ay_I"}, {"duration": 0.08, "phone": "k_E"}], "start": 5.12, "startOffset": 80, "word": "like"}, {"alignedWord": "rats", "case": "success", "end": 5.75, "endOffset": 89, "phones": [{"duration": 0.12, "phone": "r_B"}, {"duration": 0.07, "phone": "ae_I"}, {"duration": 0.07, "phone": "t_I"}, {"duration": 0.08, "phone": "s_E"}], "start": 5.41, "startOffset": 85, "word": "rats"}, {"alignedWord": "boys", "case": "success", "end": 6.08, "endOffset": 94, "phones": [{"duration": 0.07, "phone": "b_B"}, {"duration": 0.18, "phone": "oy_I"}, {"duration": 0.08, "phone": "z_E"}], "start": 5.75, "startOffset": 90, "word": "boys"}, {"alignedWord": "good", "case": "success", "end": 6.41, "endOffset": 99, "phones": [{"duration": 0.08, "phone": "g_B"}, {"duration": 0.17, "phone": "uh_I"}, {"duration": 0.08, "phone": "d_E"}], "start": 6.08, "startOffset": 95, "word": "good"}, {"alignedWord": "wear", "case": "success", "end": 6.72, "endOffset": 104, "phones": [{"duration": 0.08, "phone": "w_B"}, {"duration": 0.09, "phone": "eh_I"}, {"duration": 0.14, "phone": "r_E"}], "start": 6.41, "startOffset": 100, "word": "wear"}, {"alignedWord": "dogs", "case": "success", "end": 7.050000000000001, "endOffset": 109, "phones": [{"duration": 0.07, "phone": "d_B"}, {"duration": 0.14, "phone": "ao_I"}, {"duration": 0.06, "phone": "g_I"}, {"duration": 0.05, "phone": "z_E"}], "start": 6.73, "startOffset": 105, "word": "dogs"}, {"alignedWord": "things", "case": "success", "end": 7.36, "endOffset": 116, "phones": [{"duration": 0.07, "phone": "th_B"}, {"duration": 0.07, "phone": "ih_I"}, {"duration": 0.07, "phone": "ng_I"}, {"duration": 0.08, "phone": "z_E"}], "start": 7.07, "startOffset": 110, "word": "things"}, {"alignedWord": "tall", "case": "success", "end": 7.69, "endOffset": 121, "phones": [{"duration": 0.08, "phone": "t_B"}, {"duration": 0.14, "phone": "ao_I"}, {"duration": 0.11, "phone": "l_E"}], "start": 7.36, "startOffset": 117, "word": "tall"}, {"alignedWord": "sell", "case": "success", "end": 8.01, "endOffset": 126, "phones": [{"duration": 0.08, "phone": "s_B"}, {"duration": 0.12, "phone": "eh_I"}, {"duration": 0.11, "phone": "l_E"}], "start": 7.7, "startOffset": 122, "word": "sell"}, {"alignedWord": "kings", "case": "success", "end": 8.309999999999999, "endOffset": 132, "phones": [{"duration": 0.05, "phone": "k_B"}, {"duration": 0.11, "phone": "ih_I"}, {"duration": 0.07, "phone": "ng_I"}, {"duration": 0.06, "phone": "z_E"}], "start": 8.02, "startOffset": 127, "word": "kings"}, {"alignedWord": "things", "case": "success", "end": 8.62, "endOffset": 139, "phones": [{"duration": 0.08, "phone": "th_B"}, {"duration": 0.07, "phone": "ih_I"}, {"duration": 0.07, "phone": "ng_I"}, {"duration": 0.06, "phone": "z_E"}], "start": 8.34, "startOffset": 133, "word": "things"}, {"alignedWord": "sad", "case": "success", "end": 8.949999, "endOffset": 143, "phones": [{"duration": 0.1, "phone": "s_B"}, {"duration": 0.13, "phone": "ae_I"}, {"duration": 0.08, "phone": "d_E"}], "start": 8.639999, "startOffset": 140, "word": "sad"}, {"alignedWord": "like", "case": "success", "end": 9.260000000000002, "endOffset": 148, "phones": [{"duration": 0.1, "phone": "l_B"}, {"duration": 0.09, "phone": "ay_I"}, {"duration": 0.11, "phone": "k_E"}], "start": 8.96, "startOffset": 144, "word": "like"}, {"alignedWord": "girls", "case": "success", "end": 9.6, "endOffset": 154, "phones": [{"duration": 0.08, "phone": "g_B"}, {"duration": 0.12, "phone": "er_I"}, {"duration": 0.07, "phone": "l_I"}, {"duration": 0.07, "phone": "z_E"}], "start": 9.26, "startOffset": 149, "word": "girls"}, {"alignedWord": "mice", "case": "success", "end": 9.899999000000001, "endOffset": 159, "phones": [{"duration": 0.06, "phone": "m_B"}, {"duration": 0.15, "phone": "ay_I"}, {"duration": 0.09, "phone": "s_E"}], "start": 9.599999, "startOffset": 155, "word": "mice"}, {"alignedWord": "warm", "case": "success", "end": 10.23, "endOffset": 164, "phones": [{"duration": 0.08, "phone": "w_B"}, {"duration": 0.11, "phone": "ao_I"}, {"duration": 0.07, "phone": "r_I"}, {"duration": 0.06, "phone": "m_E"}], "start": 9.91, "startOffset": 160, "word": "warm"}, {"alignedWord": "burn", "case": "success", "end": 10.57, "endOffset": 169, "phones": [{"duration": 0.09, "phone": "b_B"}, {"duration": 0.17, "phone": "er_I"}, {"duration": 0.07, "phone": "n_E"}], "start": 10.24, "startOffset": 165, "word": "burn"}, {"alignedWord": "kings", "case": "success", "end": 10.89, "endOffset": 175, "phones": [{"duration": 0.06, "phone": "k_B"}, {"duration": 0.1, "phone": "ih_I"}, {"duration": 0.08, "phone": "ng_I"}, {"duration": 0.07, "phone": "z_E"}], "start": 10.58, "startOffset": 170, "word": "kings"}, {"alignedWord": "cows", "case": "success", "end": 11.189999, "endOffset": 180, "phones": [{"duration": 0.06, "phone": "k_B"}, {"duration": 0.15, "phone": "aw_I"}, {"duration": 0.09, "phone": "z_E"}], "start": 10.889999, "startOffset": 176, "word": "cows"}, {"alignedWord": "bad", "case": "success", "end": 11.51, "endOffset": 184, "phones": [{"duration": 0.08, "phone": "b_B"}, {"duration": 0.14, "phone": "ae_I"}, {"duration": 0.09, "phone": "d_E"}], "start": 11.2, "startOffset": 181, "word": "bad"}, {"alignedWord": "kick", "case": "success", "end": 11.799999999999999, "endOffset": 189, "phones": [{"duration": 0.09, "phone": "k_B"}, {"duration": 0.12, "phone": "ih_I"}, {"duration": 0.05, "phone": "k_E"}], "start": 11.54, "startOffset": 185, "word": "kick"}, {"alignedWord": "girls", "case": "success", "end": 12.149999, "endOffset": 195, "phones": [{"duration": 0.09, "phone": "g_B"}, {"duration": 0.12, "phone": "er_I"}, {"duration": 0.06, "phone": "l_I"}, {"duration": 0.07, "phone": "z_E"}], "start": 11.809999, "startOffset": 190, "word": "girls"}, {"alignedWord": "birds", "case": "success", "end": 12.48, "endOffset": 201, "phones": [{"duration": 0.08, "phone": "b_B"}, {"duration": 0.14, "phone": "er_I"}, {"duration": 0.06, "phone": "d_I"}, {"duration": 0.03, "phone": "z_E"}], "start": 12.17, "startOffset": 196, "word": "birds"}, {"alignedWord": "fast", "case": "success", "end": 12.790000000000001, "endOffset": 206, "phones": [{"duration": 0.08, "phone": "f_B"}, {"duration": 0.12, "phone": "ae_I"}, {"duration": 0.06, "phone": "s_I"}, {"duration": 0.05, "phone": "t_E"}], "start": 12.48, "startOffset": 202, "word": "fast"}, {"alignedWord": "hold", "case": "success", "end": 13.099999, "endOffset": 211, "phones": [{"duration": 0.07, "phone": "hh_B"}, {"duration": 0.06, "phone": "ow_I"}, {"duration": 0.11, "phone": "l_I"}, {"duration": 0.06, "phone": "d_E"}], "start": 12.799999, "startOffset": 207, "word": "hold"}, {"alignedWord": "hands", "case": "success", "end": 13.41, "endOffset": 217, "phones": [{"duration": 0.07, "phone": "hh_B"}, {"duration": 0.09, "phone": "ae_I"}, {"duration": 0.07, "phone": "n_I"}, {"duration": 0.07, "phone": "z_E"}], "start": 13.11, "startOffset": 212, "word": "hands"}, {"alignedWord": "wives", "case": "success", "end": 13.709999999999999, "endOffset": 223, "phones": [{"duration": 0.1, "phone": "w_B"}, {"duration": 0.11, "phone": "ay_I"}, {"duration": 0.06, "phone": "v_I"}, {"duration": 0.02, "phone": "z_E"}], "start": 13.42, "startOffset": 218, "word": "wives"}, {"alignedWord": "soft", "case": "success", "end": 14.08, "endOffset": 228, "phones": [{"duration": 0.12, "phone": "s_B"}, {"duration": 0.12, "phone": "ao_I"}, {"duration": 0.07, "phone": "f_I"}, {"duration": 0.06, "phone": "t_E"}], "start": 13.71, "startOffset": 224, "word": "soft"}, {"alignedWord": "take", "case": "success", "end": 14.4, "endOffset": 233, "phones": [{"duration": 0.11, "phone": "t_B"}, {"duration": 0.12, "phone": "ey_I"}, {"duration": 0.08, "phone": "k_E"}], "start": 14.09, "startOffset": 229, "word": "take"}, {"alignedWord": "hands", "case": "success", "end": 14.700000000000001, "endOffset": 239, "phones": [{"duration": 0.06, "phone": "hh_B"}, {"duration": 0.09, "phone": "ae_I"}, {"duration": 0.07, "phone": "n_I"}, {"duration": 0.08, "phone": "z_E"}], "start": 14.4, "startOffset": 234, "word": "hands"}, {"alignedWord": "things", "case": "success", "end": 15.019999, "endOffset": 246, "phones": [{"duration": 0.1, "phone": "th_B"}, {"duration": 0.07, "phone": "ih_I"}, {"duration": 0.07, "phone": "ng_I"}, {"duration": 0.06, "phone": "z_E"}], "start": 14.719999, "startOffset": 240, "word": "things"}, {"alignedWord": "fun", "case": "success", "end": 15.34, "endOffset": 250, "phones": [{"duration": 0.11, "phone": "f_B"}, {"duration": 0.13, "phone": "ah_I"}, {"duration": 0.07, "phone": "n_E"}], "start": 15.03, "startOffset": 247, "word": "fun"}, {"alignedWord": "drive", "case": "success", "end": 15.639999, "endOffset": 256, "phones": [{"duration": 0.05, "phone": "d_B"}, {"duration": 0.08, "phone": "r_I"}, {"duration": 0.1, "phone": "ay_I"}, {"duration": 0.06, "phone": "v_E"}], "start": 15.349999, "startOffset": 251, "word": "drive"}, {"alignedWord": "stars", "case": "success", "end": 16.0, "endOffset": 262, "phones": [{"duration": 0.06, "phone": "s_B"}, {"duration": 0.06, "phone": "t_I"}, {"duration": 0.07, "phone": "aa_I"}, {"duration": 0.09, "phone": "r_I"}, {"duration": 0.07, "phone": "z_E"}], "start": 15.65, "startOffset": 257, "word": "stars"}, {"alignedWord": "kids", "case": "success", "end": 16.3, "endOffset": 267, "phones": [{"duration": 0.06, "phone": "k_B"}, {"duration": 0.11, "phone": "ih_I"}, {"duration": 0.07, "phone": "d_I"}, {"duration": 0.06, "phone": "z_E"}], "start": 16.0, "startOffset": 263, "word": "kids"}, {"alignedWord": "rich", "case": "success", "end": 16.469999, "endOffset": 272, "phones": [{"duration": 0.07, "phone": "r_B"}, {"duration": 0.1, "phone": "ih_I"}], "start": 16.299999, "startOffset": 268, "word": "rich"}]